LICENSE.txt
MANIFEST.in
README.rst
pyproject.toml
requirements-6.1.txt
requirements-6.2.txt
setup.cfg
setup.py
docs/Makefile
docs/changes.rst
docs/client-api.rst
docs/cms-api.rst
docs/conf.py
docs/index.rst
docs/index_de.rst
docs/index_el.rst
docs/index_fr.rst
docs/index_nl.rst
docs/install.rst
docs/xml.rst
docs/implementation/index.rst
docs/implementation/api/index.rst
docs/implementation/api/client/authentication.rst
docs/implementation/api/client/client.rst
docs/implementation/api/client/country.rst
docs/implementation/api/client/model.rst
docs/implementation/api/client/navigation.rst
docs/implementation/api/client/profile.rst
docs/implementation/api/client/sector.rst
docs/implementation/api/client/survey.rst
docs/implementation/api/client/update.rst
docs/implementation/api/client/utils.rst
docs/implementation/api/client/browser/client.rst
docs/implementation/api/client/browser/company.rst
docs/implementation/api/client/browser/country.rst
docs/implementation/api/client/browser/login.rst
docs/implementation/api/client/browser/module.rst
docs/implementation/api/client/browser/publish.rst
docs/implementation/api/client/browser/report.rst
docs/implementation/api/client/browser/risk.rst
docs/implementation/api/client/browser/sector.rst
docs/implementation/api/client/browser/session.rst
docs/implementation/api/client/browser/settings.rst
docs/implementation/api/client/browser/survey.rst
docs/implementation/api/client/browser/training.rst
docs/implementation/api/client/browser/webhelpers.rst
docs/implementation/api/content/behaviors.rst
docs/implementation/api/content/behaviour.rst
docs/implementation/api/content/country.rst
docs/implementation/api/content/countrymanager.rst
docs/implementation/api/content/documentation.rst
docs/implementation/api/content/fti.rst
docs/implementation/api/content/help.rst
docs/implementation/api/content/login.rst
docs/implementation/api/content/module.rst
docs/implementation/api/content/profilequestion.rst
src/Euphorie.egg-info/PKG-INFO
src/Euphorie.egg-info/SOURCES.txt
src/Euphorie.egg-info/dependency_links.txt
src/Euphorie.egg-info/entry_points.txt
src/Euphorie.egg-info/not-zip-safe
src/Euphorie.egg-info/requires.txt
src/Euphorie.egg-info/top_level.txt
