Metadata-Version: 2.4
Name: Euphorie
Version: 19.1.7
Summary: Euphorie Risk Assessment tool
Home-page: https://euphorie.readthedocs.org/en/latest/
Author: Wichert Akkerman and Syslab.com
Author-email: info@syslab.com
License: GPL
Keywords: euphorie OiRA Interactive Risk Assessment
Classifier: Development Status :: 5 - Production/Stable
Classifier: Environment :: Web Environment
Classifier: Framework :: Plone
Classifier: Framework :: Plone :: 6.1
Classifier: Framework :: Plone :: 6.2
Classifier: License :: OSI Approved :: GNU General Public License (GPL)
Classifier: Programming Language :: Python :: 3
Classifier: Programming Language :: Python :: 3.11
Classifier: Programming Language :: Python :: 3.12
Classifier: Programming Language :: Python :: 3.13
Classifier: Topic :: Internet :: WWW/HTTP
Classifier: Topic :: Software Development :: Libraries :: Python Modules
Requires-Python: >=3.11
License-File: LICENSE.txt
Requires-Dist: AccessControl
Requires-Dist: alembic
Requires-Dist: anytree
Requires-Dist: Chameleon
Requires-Dist: decorator
Requires-Dist: ftw.upgrade
Requires-Dist: lxml
Requires-Dist: markdownify
Requires-Dist: nltk
Requires-Dist: NuPlone>=4.0.1
Requires-Dist: openpyxl
Requires-Dist: path.py
Requires-Dist: Plone>=6.0
Requires-Dist: plone.api
Requires-Dist: plone.app.imagecropping
Requires-Dist: plone.app.redirector
Requires-Dist: plone.app.vocabularies
Requires-Dist: plone.app.z3cform
Requires-Dist: plone.behavior
Requires-Dist: plone.dexterity
Requires-Dist: plone.formwidget.namedfile
Requires-Dist: plone.memoize
Requires-Dist: plone.namedfile
Requires-Dist: plone.patternslib
Requires-Dist: plonestatic.euphorie
Requires-Dist: plone.uuid
Requires-Dist: Products.membrane>=4.999999
Requires-Dist: py-bcrypt
Requires-Dist: python-docx
Requires-Dist: repoze.formapi
Requires-Dist: scikit-learn
Requires-Dist: setuptools
Requires-Dist: sh
Requires-Dist: SQLAlchemy>=1.2.999999
Requires-Dist: stoneagehtml
Requires-Dist: user_agents
Requires-Dist: weasyprint
Requires-Dist: z3c.form
Requires-Dist: z3c.saconfig
Requires-Dist: zope.configuration
Requires-Dist: zope.i18nmessageid
Requires-Dist: zope.interface
Requires-Dist: zope.schema
Provides-Extra: sphinx
Requires-Dist: Sphinx>=1.0; extra == "sphinx"
Requires-Dist: repoze.sphinx.autointerface; extra == "sphinx"
Provides-Extra: tests
Requires-Dist: plone.app.testing; extra == "tests"
Dynamic: author
Dynamic: author-email
Dynamic: classifier
Dynamic: description
Dynamic: home-page
Dynamic: keywords
Dynamic: license
Dynamic: license-file
Dynamic: provides-extra
Dynamic: requires-dist
Dynamic: requires-python
Dynamic: summary
